qiskit_pasqal_provider/__init__.py
qiskit_pasqal_provider/exception.py
qiskit_pasqal_provider/utils.py
qiskit_pasqal_provider/version.py
qiskit_pasqal_provider/providers/__init__.py
qiskit_pasqal_provider/providers/abstract_base.py
qiskit_pasqal_provider/providers/gate.py
qiskit_pasqal_provider/providers/jobs.py
qiskit_pasqal_provider/providers/layouts.py
qiskit_pasqal_provider/providers/provider.py
qiskit_pasqal_provider/providers/pulse_utils.py
qiskit_pasqal_provider/providers/result.py
qiskit_pasqal_provider/providers/sampler.py
qiskit_pasqal_provider/providers/target.py
qiskit_pasqal_provider/providers/backends/__init__.py
qiskit_pasqal_provider/providers/backends/emu_mps.py
qiskit_pasqal_provider/providers/backends/emu_remote.py
qiskit_pasqal_provider/providers/backends/local.py
qiskit_pasqal_provider/providers/backends/qpu.py
qiskit_pasqal_provider/providers/backends/qutip.py
qiskit_pasqal_provider/providers/backends/remote.py
qiskit_pasqal_provider-0.1.1.dist-info/licenses/LICENSE.txt
qiskit_pasqal_provider-0.1.1.dist-info/METADATA
qiskit_pasqal_provider-0.1.1.dist-info/WHEEL
qiskit_pasqal_provider-0.1.1.dist-info/top_level.txt
qiskit_pasqal_provider-0.1.1.dist-info/RECORD
