Metadata-Version: 2.4
Name: qiskit_pasqal_provider
Version: 0.1.1
Summary: Qiskit provider for Pasqal's analog neutral atom QPUs
Author-email: Eduardo Maschio <eduardo.maschio@pasqal.com>, Aleksander Wennersteen <aleksander.wennersteen@pasqal.com>, Roland Guichard <roland.guichard@pasqal.com>, Pasqal <contact@pasqal.com>
License:                     Copyright 2021 IBM and its contributors
Project-URL: Homepage, https://github.com/qiskit-community/qiskit-pasqal-provider
Project-URL: Bug Tracker, https://github.com/qiskit-community/qiskit-pasqal-provider/issues
Requires-Python: >=3.11
License-File: LICENSE.txt
Requires-Dist: certifi>=2021.5.30
Requires-Dist: importlib_metadata>=4.8.1
Requires-Dist: qiskit<3,>=1.0
Requires-Dist: pulser>=1.5
Requires-Dist: pasqal-cloud~=0.12.5
Provides-Extra: mps
Requires-Dist: emu-mps>=2; extra == "mps"
Provides-Extra: dev
Requires-Dist: coverage>=5.5; extra == "dev"
Requires-Dist: pylint>=2.9.5; extra == "dev"
Requires-Dist: nbqa>=1.1.1; extra == "dev"
Requires-Dist: treon>=0.1.3; extra == "dev"
Requires-Dist: pytest>=6.2.5; extra == "dev"
Requires-Dist: pytest-randomly>=1.2.0; extra == "dev"
Requires-Dist: mypy>=0.780; extra == "dev"
Requires-Dist: mypy-extensions>=0.4.3; extra == "dev"
Requires-Dist: jupyter-sphinx>=0.3.2; extra == "dev"
Requires-Dist: nbsphinx>=0.8.8; extra == "dev"
Requires-Dist: sphinx-autodoc-typehints>=1.17.0; extra == "dev"
Requires-Dist: qiskit-sphinx-theme~=1.16.0; extra == "dev"
Requires-Dist: reno>=3.5.0; extra == "dev"
Requires-Dist: black[jupyter]~=24.10; extra == "dev"
Dynamic: license-file
